read_comports_tonet/__init__.py
read_comports_tonet/app.py
read_comports_tonet-0.0.1.dist-info/LICENSE
read_comports_tonet-0.0.1.dist-info/METADATA
read_comports_tonet-0.0.1.dist-info/WHEEL
read_comports_tonet-0.0.1.dist-info/top_level.txt
read_comports_tonet-0.0.1.dist-info/RECORD
