Metadata-Version: 2.1
Name: read-comports-tonet
Version: 0.0.1
Summary: Easy read data from COM ports and send them over the server(net) example in your arduino or raspberrypi project
Home-page: https://github.com/yosiaLukumai/Reading-data-From-Ports
Author: Yosia Lukumai
Author-email: yosialukumai@gmail.com
License: MIT
Keywords: python,read com ports,read com ports data send to net,read com data and send to thingsspeak,proteus data to server,arduino to server,rasberrypi to server
Platform: UNKNOWN
Classifier: Development Status :: 1 - Planning
Classifier: Intended Audience :: Developers
Classifier: Programming Language :: Python :: 3
Classifier: Operating System :: Unix
Classifier: Operating System :: MacOS :: MacOS X
Classifier: Operating System :: Microsoft :: Windows
License-File: LICENSE
Requires-Dist: requests (>=2.20.0)
Requires-Dist: schedule (>=1.0.0)
Requires-Dist: pyserial (>=3.0)
